synthetic/__init__.py
synthetic/commands/__init__.py
synthetic/commands/base.py
synthetic/commands/signature.py
synthetic/exceptions.py
synthetic/hooks/__init__.py
synthetic/hooks/base.py
synthetic/hooks/command.py
synthetic/transformer.py
synthetic_transformers-0.3.1.dist-info/LICENSE
synthetic_transformers-0.3.1.dist-info/METADATA
synthetic_transformers-0.3.1.dist-info/WHEEL
synthetic_transformers-0.3.1.dist-info/RECORD
