Metadata-Version: 2.3
Name: synthetic-transformers
Version: 0.3.1
Summary: transformers library new generate API
License: LICENSE
Author: Carlos Fernandez
Author-email: carlos.ferlo@outlook.com
Requires-Python: >=3.10,<3.14
Classifier: License :: Other/Proprietary License
Classifier: Programming Language :: Python :: 3
Classifier: Programming Language :: Python :: 3.10
Classifier: Programming Language :: Python :: 3.11
Classifier: Programming Language :: Python :: 3.12
Classifier: Programming Language :: Python :: 3.13
Requires-Dist: jinja2 (>=3.1.6,<4.0.0)
Requires-Dist: torch (>=2.8.0,<3.0.0)
Requires-Dist: transformers (>=4.56.1,<5.0.0)
